sonosthesia_audio_pipeline/__init__.py
sonosthesia_audio_pipeline/__main__.py
sonosthesia_audio_pipeline/analysis.py
sonosthesia_audio_pipeline/check.py
sonosthesia_audio_pipeline/conversion.py
sonosthesia_audio_pipeline/inspection.py
sonosthesia_audio_pipeline/pipeline.py
sonosthesia_audio_pipeline/preview.py
sonosthesia_audio_pipeline/separation.py
sonosthesia_audio_pipeline/utils.py
sonosthesia_audio_pipeline-2.1.0.dist-info/LICENSE
sonosthesia_audio_pipeline-2.1.0.dist-info/METADATA
sonosthesia_audio_pipeline-2.1.0.dist-info/WHEEL
sonosthesia_audio_pipeline-2.1.0.dist-info/top_level.txt
sonosthesia_audio_pipeline-2.1.0.dist-info/RECORD
