Metadata-Version: 2.1
Name: sonosthesia_audio_pipeline
Version: 2.1.0
Summary: Sonosthesia tools for baking audio analysis data
Author-email: Sonosthesia <jonathan@sonosthesia.com>
License: MIT License
Project-URL: Homepage, https://github.com/jbat100/sonosthesia-audio-pipeline
Project-URL: Source, https://github.com/jbat100/sonosthesia-audio-pipeline
Project-URL: Issues, https://github.com/jbat100/sonosthesia-audio-pipeline/issues
Classifier: Programming Language :: Python :: 3.9
Classifier: Programming Language :: Python :: 3.10
Classifier: Programming Language :: Python :: 3.11
Classifier: Programming Language :: Python :: 3.12
Classifier: License :: OSI Approved :: MIT License
Classifier: Operating System :: OS Independent
Requires-Python: >=3.9
License-File: LICENSE
Requires-Dist: matplotlib
Requires-Dist: scipy
Requires-Dist: librosa
Requires-Dist: msgpack
Requires-Dist: demucs
Requires-Dist: termcolor
Requires-Dist: colorama
Requires-Dist: jsonschema
Requires-Dist: diffq
